LICENSE
README.md
setup.cfg
setup.py
pydantic2graphene/__init__.py
pydantic2graphene/converter.py
pydantic2graphene/converter_helpers.py
pydantic2graphene/errors.py
pydantic2graphene/fields.py
pydantic2graphene/types.py
pydantic2graphene/version.py
pydantic2graphene.egg-info/PKG-INFO
pydantic2graphene.egg-info/SOURCES.txt
pydantic2graphene.egg-info/dependency_links.txt
pydantic2graphene.egg-info/requires.txt
pydantic2graphene.egg-info/top_level.txt