Metadata-Version: 2.1
Name: pydantic2graphene
Version: 0.5.1
Summary: Easy way to convert pydantic2graphene models to graphene objects.
Home-page: https://github.com/lfvilella/pydantic2graphene
Author: Luis Felipe Vilella
Author-email: vilella.luisfelipe@gmail.com
License: MIT
Download-URL: https://github.com/lfvilella/pydantic2graphene/archive/v0.5.1.tar.gz
Keywords: python,api,graphql,graphene,pydantinc
Platform: UNKNOWN
Classifier: Development Status :: 5 - Production/Stable
Classifier: Programming Language :: Python
Classifier: Programming Language :: Python :: 3
Classifier: Programming Language :: Python :: 3 :: Only
Classifier: Programming Language :: Python :: 3.6
Classifier: Programming Language :: Python :: 3.7
Classifier: Programming Language :: Python :: 3.8
Classifier: Programming Language :: Python :: 3.9
Classifier: Programming Language :: Python :: 3.10
Classifier: Intended Audience :: Developers
Classifier: Intended Audience :: Information Technology
Classifier: License :: OSI Approved :: MIT License
Classifier: Operating System :: Unix
Classifier: Operating System :: POSIX :: Linux
Classifier: Environment :: Console
Classifier: Environment :: MacOS X
Classifier: Topic :: Software Development :: Libraries :: Python Modules
Classifier: Topic :: Internet
Requires-Python: >=3.6,<3.11
